{
    "showOnHome": false,
    "title": "NEXT IPO: تطبيق جوال لتتبع الاكتتابات العامة الأولية",
    "content": [
        {
            "type": "text",
            "value": "NEXT IPO هو تطبيق Flutter مصمم لـ *تتبع وعرض المعلومات حول الاكتتابات العامة الأولية (IPOs)* القادمة. يوفر التطبيق واجهة سهلة الاستخدام لعرض تفاصيل الاكتتاب العام وتخصيص الإعدادات والبقاء على اطلاع بأحدث العروض."
        },
        {
            "type": "image",
            "value": "/assets/ipos/screen.png"
        },
        {
            "type": "text",
            "value": "لقطة شاشة لتطبيق NEXT IPO تعرض الشاشة الرئيسية وواجهة القائمة."
        }
    ],
    "shortDescription": "تطبيق Flutter لتتبع وعرض معلومات حول الاكتتابات العامة الأولية القادمة مع إعدادات قابلة للتخصيص وبيانات في الوقت الفعلي.",
    "metaDescription": "اكتشف NEXT IPO، تطبيق جوال مبني بـ Flutter لتتبع الاكتتابات العامة الأولية القادمة. يتميز بإعدادات قابلة للتخصيص وبيانات في الوقت الفعلي من السوق المالية السعودية (تداول) وواجهة سهلة الاستخدام.",
    "keywords": [
        "تطبيق تتبع الاكتتابات",
        "تطوير تطبيق Flutter",
        "الاكتتابات العامة في السوق المالية السعودية",
        "تطبيق التمويل للجوال",
        "بيانات الاكتتابات في الوقت الفعلي"
    ],
    "client": null,
    "event": null,
    "date": "2025-08-31",
    "categories": [
        "تطوير تطبيقات الجوال",
        "التمويل"
    ],
    "tags": [
        "Flutter",
        "Dart",
        "Web Scraping",
        "IPO",
        "State Management",
        "Responsive Design",
        "Multi-language Support"
    ],
    "objectives": [
        "توفير واجهة سهلة الاستخدام لعرض تفاصيل الاكتتابات العامة القادمة.",
        "السماح للمستخدمين بتخصيص عرضهم عن طريق اختيار الأسواق ونطاقات التاريخ.",
        "دعم لغات متعددة (الإنجليزية والعربية).",
        "جلب بيانات الاكتتابات في الوقت الفعلي من موقع السوق المالية السعودية (تداول).",
        "تنفيذ تصميم متجاوب (responsive design) للعرض الأمثل على مختلف الأجهزة."
    ],
    "functionality": [
        {
            "featureName": "قائمة الاكتتابات الديناميكية",
            "description": "عرض الاكتتابات العامة القادمة بتنسيق بطاقة قابلة للتوسيع."
        },
        {
            "featureName": "دعم السمات",
            "description": "الاختيار بين السمات الداكنة والفاتحة لعرض مريح."
        },
        {
            "featureName": "إعدادات قابلة للتخصيص",
            "description": "اختيار أسواق محددة (الكل، السوق الرئيسية، نمو - السوق الموازية، الصكوك) وتعيين نطاقات تاريخ مخصصة لقوائم الاكتتابات."
        },
        {
            "featureName": "دعم متعدد اللغات",
            "description": "متاح باللغتين الإنجليزية والعربية. (قريباً)"
        },
        {
            "featureName": "تصميم متجاوب",
            "description": "يستخدم تخطيط شبكة متداخلة (staggered grid layout) للعرض الأمثل على أحجام الأجهزة المختلفة."
        },
        {
            "featureName": "بيانات في الوقت الفعلي",
            "description": "جلب أحدث معلومات الاكتتابات وإدارة ملفات تعريف الارتباط (cookies) لقوائم محدثة."
        }
    ],
    "technicalDetails": {
        "frontend": [
            "Flutter"
        ],
        "backend": [],
        "database": [],
        "libraries": [],
        "frameworks": [
            "Dart"
        ],
        "tools": [
            "Git"
        ],
        "hosting": ""
    },
    "design": {
        "aesthetic": "تطبيق جوال بوضع داكن مع تصميم حديث وبسيط، يستخدم لون أصفر ساطع لإبراز المعلومات المهمة.",
        "colorPalette": [
            "#0d1620",
            "#172536",
            "#1e2735",
            "#ffd500",
            "#EAEAEB",
            "#FFFFFF"
        ],
        "typography": [
            "Roboto"
        ],
        "responsiveness": "مصمم للأجهزة المحمولة، مع تخطيط واضح محسن للتفاعل باللمس.",
        "accessibility": "التباين العالي بين الخلفية الداكنة والنص/الأيقونات الفاتحة يشير إلى قابلية قراءة جيدة."
    },
    "media": [
        {
            "type": "video",
            "url": "/assets/ipos/NEXTIPOsVideo.mp4",
            "alt": "عرض فيديو لميزات ووظائف تطبيق NEXT IPO",
            "caption": "عرض فيديو"
        }
    ],
    "outcomes": [
        "تطوير تطبيق Flutter وظيفي يعرض معلومات الاكتتابات العامة في الوقت الفعلي.",
        "تنفيذ إعدادات قابلة للتخصيص من قبل المستخدم لاختيار السوق ونطاقات التاريخ.",
        "توفير تصميم متجاوب يتكيف مع أحجام الشاشات المختلفة."
    ],
    "challenges": [
        {
            "challenge": "استخراج بيانات الاكتتابات من موقع السوق المالية السعودية.",
            "solution": "استخدام تقنيات استخراج البيانات من الويب (web scraping)، وإدارة ملفات تعريف الارتباط، وإرسال طلبات HTTP لاسترداد معلومات محدثة."
        },
        {
            "challenge": "تحليل وتنسيق بيانات الاكتتابات المستردة للعرض.",
            "solution": "التعامل مع حقول بيانات مختلفة مثل اسم الشركة، ومعرف الاكتتاب، وسعر الإصدار، وتواريخ الطرح."
        }
    ],
    "clientFeedback": [],
    "projectPage": "/projects/next-ipo.html",
    "linkToProject": "",
    "repository": "https://github.com/FS-17/NEXT_IPOs",
    "notes": "هذا المشروع للأغراض التعليمية فقط. ليس مخصصاً للاستخدام التجاري أو كنصيحة مالية."
}